fmp/__init__.py
fmp/config.py
fmp/consts.py
fmp/errors.py
fmp/repository/__init__.py
fmp/repository/errors.py
fmp/repository/models.py
fmp/repository/mongo.py
fmp/repository/utils.py
fmp_core-1.1.0.dist-info/METADATA
fmp_core-1.1.0.dist-info/WHEEL
fmp_core-1.1.0.dist-info/top_level.txt
fmp_core-1.1.0.dist-info/RECORD
